{"lastUsed":1620692880412,"path":"C:\/javaCamp\/javaCamp","projectCount":7,"recentFiles":[{"path":"\/interfaces\/src\/interfaces","parentWorkspace":"C:\/javaCamp\/javaCamp","name":"EmailLogger.java","lastModified":1619903741851,"locationURI":"file:\/C:\/javaCamp\/javaCamp\/interfaces\/src\/interfaces\/EmailLogger.java"},{"path":"\/nLayeredDemo\/src\/nLayeredDemo\/dataAccess\/concretes","parentWorkspace":"C:\/javaCamp\/javaCamp","name":"HibernateProductDao.java","lastModified":1620507678465,"locationURI":"file:\/C:\/javaCamp\/javaCamp\/nLayeredDemo\/src\/nLayeredDemo\/dataAccess\/concretes\/HibernateProductDao.java"},{"path":"\/oopIntro\/src\/oopIntro","parentWorkspace":"C:\/javaCamp\/javaCamp","name":"ProductManager.java","lastModified":1619637271911,"locationURI":"file:\/C:\/javaCamp\/javaCamp\/oopIntro\/src\/oopIntro\/ProductManager.java"},{"path":"\/inheritance2\/src\/inheritance2","parentWorkspace":"C:\/javaCamp\/javaCamp","name":"EmailLogger.java","lastModified":1619645584272,"locationURI":"file:\/C:\/javaCamp\/javaCamp\/inheritance2\/src\/inheritance2\/EmailLogger.java"},{"path":"\/interfaces\/src\/interfaces","parentWorkspace":"C:\/javaCamp\/javaCamp","name":"Customer.java","lastModified":1619901639212,"locationURI":"file:\/C:\/javaCamp\/javaCamp\/interfaces\/src\/interfaces\/Customer.java"},{"path":"\/oopIntro\/src\/oopIntro","parentWorkspace":"C:\/javaCamp\/javaCamp","name":"Category.java","lastModified":1619639362061,"locationURI":"file:\/C:\/javaCamp\/javaCamp\/oopIntro\/src\/oopIntro\/Category.java"},{"path":"\/inheritance\/src\/inheritance","parentWorkspace":"C:\/javaCamp\/javaCamp","name":"CorporateCustomer.java","lastModified":1619642002530,"locationURI":"file:\/C:\/javaCamp\/javaCamp\/inheritance\/src\/inheritance\/CorporateCustomer.java"},{"path":"\/northwind\/src\/main\/resources","parentWorkspace":"C:\/javaCamp\/javaCamp","name":"application.properties","lastModified":1620529472447,"locationURI":"file:\/C:\/javaCamp\/javaCamp\/northwind\/src\/main\/resources\/application.properties"},{"path":"\/nLayeredDemo\/src\/nLayeredDemo","parentWorkspace":"C:\/javaCamp\/javaCamp","name":"Main.java","lastModified":1620248519058,"locationURI":"file:\/C:\/javaCamp\/javaCamp\/nLayeredDemo\/src\/nLayeredDemo\/Main.java"},{"path":"\/northwind\/src\/main\/java\/kodlamaio\/northwind\/business\/concretes","parentWorkspace":"C:\/javaCamp\/javaCamp","name":"ProductManager.java","lastModified":1620692737717,"locationURI":"file:\/C:\/javaCamp\/javaCamp\/northwind\/src\/main\/java\/kodlamaio\/northwind\/business\/concretes\/ProductManager.java"},{"path":"\/nLayeredDemo\/src\/nLayeredDemo\/dataAccess\/concretes","parentWorkspace":"C:\/javaCamp\/javaCamp","name":"AbcProductDao.java","lastModified":1620507678465,"locationURI":"file:\/C:\/javaCamp\/javaCamp\/nLayeredDemo\/src\/nLayeredDemo\/dataAccess\/concretes\/AbcProductDao.java"},{"path":"\/nLayeredDemo\/src\/nLayeredDemo\/jLogger","parentWorkspace":"C:\/javaCamp\/javaCamp","name":"JLoggerManager.java","lastModified":1620248685157,"locationURI":"file:\/C:\/javaCamp\/javaCamp\/nLayeredDemo\/src\/nLayeredDemo\/jLogger\/JLoggerManager.java"},{"path":"\/nLayeredDemo\/src\/nLayeredDemo\/core","parentWorkspace":"C:\/javaCamp\/javaCamp","name":"LoggerService.java","lastModified":1620248098438,"locationURI":"file:\/C:\/javaCamp\/javaCamp\/nLayeredDemo\/src\/nLayeredDemo\/core\/LoggerService.java"},{"path":"\/interfaces\/src\/interfaces","parentWorkspace":"C:\/javaCamp\/javaCamp","name":"Utils.java","lastModified":1619905789064,"locationURI":"file:\/C:\/javaCamp\/javaCamp\/interfaces\/src\/interfaces\/Utils.java"},{"path":"\/interfaces\/src\/interfaces","parentWorkspace":"C:\/javaCamp\/javaCamp","name":"Main.java","lastModified":1619904506383,"locationURI":"file:\/C:\/javaCamp\/javaCamp\/interfaces\/src\/interfaces\/Main.java"},{"path":"\/oopIntro\/src\/oopIntro","parentWorkspace":"C:\/javaCamp\/javaCamp","name":"Main.java","lastModified":1620511910371,"locationURI":"file:\/C:\/javaCamp\/javaCamp\/oopIntro\/src\/oopIntro\/Main.java"},{"path":"\/northwind","parentWorkspace":"C:\/javaCamp\/javaCamp","name":"pom.xml","lastModified":1620519861159,"locationURI":"file:\/C:\/javaCamp\/javaCamp\/northwind\/pom.xml"},{"path":"\/inheritance2\/src\/inheritance2","parentWorkspace":"C:\/javaCamp\/javaCamp","name":"Main.java","lastModified":1619646092847,"locationURI":"file:\/C:\/javaCamp\/javaCamp\/inheritance2\/src\/inheritance2\/Main.java"},{"path":"\/nLayeredDemo\/src\/nLayeredDemo\/business\/abstracts","parentWorkspace":"C:\/javaCamp\/javaCamp","name":"ProductService.java","lastModified":1620245269461,"locationURI":"file:\/C:\/javaCamp\/javaCamp\/nLayeredDemo\/src\/nLayeredDemo\/business\/abstracts\/ProductService.java"},{"path":"\/interfaces\/src\/interfaces","parentWorkspace":"C:\/javaCamp\/javaCamp","name":"DatabaseLogger.java","lastModified":1619900976377,"locationURI":"file:\/C:\/javaCamp\/javaCamp\/interfaces\/src\/interfaces\/DatabaseLogger.java"},{"path":"\/nLayeredDemo\/src\/nLayeredDemo\/entities\/concretes","parentWorkspace":"C:\/javaCamp\/javaCamp","name":"Product.java","lastModified":1620243748811,"locationURI":"file:\/C:\/javaCamp\/javaCamp\/nLayeredDemo\/src\/nLayeredDemo\/entities\/concretes\/Product.java"},{"path":"\/nLayeredDemo\/src\/nLayeredDemo\/core","parentWorkspace":"C:\/javaCamp\/javaCamp","name":"JLoggerManagerAdapter.java","lastModified":1620248424932,"locationURI":"file:\/C:\/javaCamp\/javaCamp\/nLayeredDemo\/src\/nLayeredDemo\/core\/JLoggerManagerAdapter.java"},{"path":"\/inheritance\/src\/inheritance","parentWorkspace":"C:\/javaCamp\/javaCamp","name":"Main.java","lastModified":1619643510039,"locationURI":"file:\/C:\/javaCamp\/javaCamp\/inheritance\/src\/inheritance\/Main.java"},{"path":"\/inheritance\/src\/inheritance","parentWorkspace":"C:\/javaCamp\/javaCamp","name":"SendikaCustomer.java","lastModified":1619643034893,"locationURI":"file:\/C:\/javaCamp\/javaCamp\/inheritance\/src\/inheritance\/SendikaCustomer.java"},{"path":"\/inheritance2\/src\/inheritance2","parentWorkspace":"C:\/javaCamp\/javaCamp","name":"DatabaseLogger.java","lastModified":1619645604389,"locationURI":"file:\/C:\/javaCamp\/javaCamp\/inheritance2\/src\/inheritance2\/DatabaseLogger.java"},{"path":"\/northwind\/src\/main\/java\/kodlamaio\/northwind\/api\/controllers","parentWorkspace":"C:\/javaCamp\/javaCamp","name":"ProductsController.java","lastModified":1620692905874,"locationURI":"file:\/C:\/javaCamp\/javaCamp\/northwind\/src\/main\/java\/kodlamaio\/northwind\/api\/controllers\/ProductsController.java"},{"path":"\/inheritance\/src\/inheritance","parentWorkspace":"C:\/javaCamp\/javaCamp","name":"IndividualCustomer.java","lastModified":1619641033907,"locationURI":"file:\/C:\/javaCamp\/javaCamp\/inheritance\/src\/inheritance\/IndividualCustomer.java"},{"path":"\/inheritance2\/src\/inheritance2","parentWorkspace":"C:\/javaCamp\/javaCamp","name":"FileLogger.java","lastModified":1619645610050,"locationURI":"file:\/C:\/javaCamp\/javaCamp\/inheritance2\/src\/inheritance2\/FileLogger.java"},{"path":"\/interfaces\/src\/interfaces","parentWorkspace":"C:\/javaCamp\/javaCamp","name":"Logger.java","lastModified":1619900439469,"locationURI":"file:\/C:\/javaCamp\/javaCamp\/interfaces\/src\/interfaces\/Logger.java"},{"path":"\/interfaces\/src\/interfaces","parentWorkspace":"C:\/javaCamp\/javaCamp","name":"CustomerManager.java","lastModified":1619905839356,"locationURI":"file:\/C:\/javaCamp\/javaCamp\/interfaces\/src\/interfaces\/CustomerManager.java"},{"path":"\/inheritance2\/src\/inheritance2","parentWorkspace":"C:\/javaCamp\/javaCamp","name":"Logger.java","lastModified":1619645660974,"locationURI":"file:\/C:\/javaCamp\/javaCamp\/inheritance2\/src\/inheritance2\/Logger.java"},{"path":"\/inheritance2\/src\/inheritance2","parentWorkspace":"C:\/javaCamp\/javaCamp","name":"LogManager.java","lastModified":1619646509620,"locationURI":"file:\/C:\/javaCamp\/javaCamp\/inheritance2\/src\/inheritance2\/LogManager.java"},{"path":"\/interfaces\/src\/interfaces","parentWorkspace":"C:\/javaCamp\/javaCamp","name":"SmsLogger.java","lastModified":1619900720868,"locationURI":"file:\/C:\/javaCamp\/javaCamp\/interfaces\/src\/interfaces\/SmsLogger.java"},{"path":"\/northwind\/src\/main\/java\/kodlamaio\/northwind\/dataAccess\/abstracts","parentWorkspace":"C:\/javaCamp\/javaCamp","name":"ProductDao.java","lastModified":1620692693615,"locationURI":"file:\/C:\/javaCamp\/javaCamp\/northwind\/src\/main\/java\/kodlamaio\/northwind\/dataAccess\/abstracts\/ProductDao.java"},{"path":"\/inheritance2\/src\/inheritance2","parentWorkspace":"C:\/javaCamp\/javaCamp","name":"CustomerManager.java","lastModified":1619645986055,"locationURI":"file:\/C:\/javaCamp\/javaCamp\/inheritance2\/src\/inheritance2\/CustomerManager.java"},{"path":"\/nLayeredDemo\/src\/nLayeredDemo\/business\/concretes","parentWorkspace":"C:\/javaCamp\/javaCamp","name":"ProductManager.java","lastModified":1620507678465,"locationURI":"file:\/C:\/javaCamp\/javaCamp\/nLayeredDemo\/src\/nLayeredDemo\/business\/concretes\/ProductManager.java"},{"path":"\/inheritance2\/src\/inheritance2","parentWorkspace":"C:\/javaCamp\/javaCamp","name":"SmsLogger.java","lastModified":1619899664321,"locationURI":"file:\/C:\/javaCamp\/javaCamp\/inheritance2\/src\/inheritance2\/SmsLogger.java"},{"path":"\/nLayeredDemo\/src\/nLayeredDemo\/dataAccess\/abstracts","parentWorkspace":"C:\/javaCamp\/javaCamp","name":"ProductDao.java","lastModified":1620244790989,"locationURI":"file:\/C:\/javaCamp\/javaCamp\/nLayeredDemo\/src\/nLayeredDemo\/dataAccess\/abstracts\/ProductDao.java"},{"path":"\/inheritance\/src\/inheritance","parentWorkspace":"C:\/javaCamp\/javaCamp","name":"CustomerManager.java","lastModified":1619643383304,"locationURI":"file:\/C:\/javaCamp\/javaCamp\/inheritance\/src\/inheritance\/CustomerManager.java"},{"path":"\/inheritance\/src\/inheritance","parentWorkspace":"C:\/javaCamp\/javaCamp","name":"Customer.java","lastModified":1619642278059,"locationURI":"file:\/C:\/javaCamp\/javaCamp\/inheritance\/src\/inheritance\/Customer.java"},{"path":"\/northwind\/src\/main\/java\/kodlamaio\/northwind\/entities\/concretes","parentWorkspace":"C:\/javaCamp\/javaCamp","name":"Product.java","lastModified":1620692648143,"locationURI":"file:\/C:\/javaCamp\/javaCamp\/northwind\/src\/main\/java\/kodlamaio\/northwind\/entities\/concretes\/Product.java"},{"path":"\/northwind\/src\/main\/java\/kodlamaio\/northwind\/business\/abstracts","parentWorkspace":"C:\/javaCamp\/javaCamp","name":"ProductService.java","lastModified":1620526643571,"locationURI":"file:\/C:\/javaCamp\/javaCamp\/northwind\/src\/main\/java\/kodlamaio\/northwind\/business\/abstracts\/ProductService.java"},{"path":"\/oopIntro\/src\/oopIntro","parentWorkspace":"C:\/javaCamp\/javaCamp","name":"Product.java","lastModified":1619637382533,"locationURI":"file:\/C:\/javaCamp\/javaCamp\/oopIntro\/src\/oopIntro\/Product.java"},{"path":"\/interfaces\/src\/interfaces","parentWorkspace":"C:\/javaCamp\/javaCamp","name":"FileLogger.java","lastModified":1619901412858,"locationURI":"file:\/C:\/javaCamp\/javaCamp\/interfaces\/src\/interfaces\/FileLogger.java"}]}